LICENSE
README.md
setup.cfg
setup.py
database/__init__.py
database/neo4j/__init__.py
database/neo4j/database_clients.py
database/neo4j/database_manager.py
wiktionary_data/__init__.py
wiktionary_data/load_graph.py
wilhelm_data_loader.egg-info/PKG-INFO
wilhelm_data_loader.egg-info/SOURCES.txt
wilhelm_data_loader.egg-info/dependency_links.txt
wilhelm_data_loader.egg-info/not-zip-safe
wilhelm_data_loader.egg-info/requires.txt
wilhelm_data_loader.egg-info/top_level.txt
wilhelm_vocabulary/__init__.py
wilhelm_vocabulary/cleanup_neo4j.py
wilhelm_vocabulary/load_all_in_parallel.py
wilhelm_vocabulary/load_ancient_greek.py
wilhelm_vocabulary/load_german.py
wilhelm_vocabulary/load_latin.py